popari/__about__.py
popari/__init__.py
popari/_binning_utils.py
popari/_canvas.py
popari/_dataset_utils.py
popari/_embedding_optimizer.py
popari/_hierarchical_view.py
popari/_parameter_optimizer.py
popari/_popari_dataset.py
popari/_simulation_utils.py
popari/analysis.py
popari/components.py
popari/genes_ncbi_mus_musculus_proteincoding.py
popari/initialization.py
popari/io.py
popari/main.py
popari/model.py
popari/plotting.py
popari/sample_for_integral.py
popari/simulation_framework.py
popari/train.py
popari/util.py
popari/mlflow/grid_search.py
popari/mlflow/train.py
popari/mlflow/util.py
popari-1.3.4.dist-info/METADATA
popari-1.3.4.dist-info/WHEEL
popari-1.3.4.dist-info/entry_points.txt
popari-1.3.4.dist-info/licenses/LICENSE
popari-1.3.4.dist-info/RECORD
