Metadata-Version: 2.4
Name: popari
Version: 1.3.4
Summary: Popari: a probabilistic graphical model for integrated spatial transcriptomics analysis
Project-URL: Homepage, https://github.com/alam-shahul/popari
Project-URL: Bug Tracker, https://github.com/alam-shahul/popari/issues
Author-email: Shahul Alam <alam.shahul@gmail.com>
License: MIT License
License-File: LICENSE
Classifier: License :: OSI Approved :: MIT License
Classifier: Operating System :: OS Independent
Classifier: Programming Language :: Python :: 3
Requires-Python: >=3.10
Requires-Dist: anndata>=0.11.0
Requires-Dist: awkward>=2.6.8
Requires-Dist: gseapy>=1.1.3
Requires-Dist: kneed>=0.8.5
Requires-Dist: leidenalg>=0.9.0
Requires-Dist: louvain>=0.8.0
Requires-Dist: matplotlib>=3.7.0
Requires-Dist: numpy<2.0
Requires-Dist: ortools<=9.4.1874
Requires-Dist: pandas>=1.5.2
Requires-Dist: pymetis>=2023.1.1
Requires-Dist: scanorama>=1.7.4
Requires-Dist: scanpy<=1.9.3
Requires-Dist: scikit-learn>=0.24.1
Requires-Dist: scipy>=1.10.1
Requires-Dist: seaborn>=0.11.1
Requires-Dist: squidpy>=1.6.2
Requires-Dist: torch>=1.13.0
Requires-Dist: tqdm>=4.60.0
Requires-Dist: umap-learn>=0.5.1
Provides-Extra: benchmark
Requires-Dist: multiprocess>=0.70.15; extra == 'benchmark'
Provides-Extra: jupyter
Requires-Dist: jupyter-resource-usage; extra == 'jupyter'
Requires-Dist: jupyterlab; extra == 'jupyter'
Requires-Dist: jupyterlab-execute-time; extra == 'jupyter'
Provides-Extra: mlflow
Requires-Dist: mlflow>=2.5.0; extra == 'mlflow'
Requires-Dist: pynvml; extra == 'mlflow'
Requires-Dist: toml>=0.10.2; extra == 'mlflow'
Provides-Extra: simulation
Requires-Dist: ipycanvas; extra == 'simulation'
Requires-Dist: jupyterlab; extra == 'simulation'
Requires-Dist: jupyterlab-execute-time; extra == 'simulation'
Provides-Extra: test
Requires-Dist: pytest; extra == 'test'
Requires-Dist: pytest-xdist; extra == 'test'
